arxiv_to_prompt/__init__.py
arxiv_to_prompt/cli.py
arxiv_to_prompt/core.py
arxiv_to_prompt-0.5.1.dist-info/licenses/LICENSE
arxiv_to_prompt-0.5.1.dist-info/METADATA
arxiv_to_prompt-0.5.1.dist-info/WHEEL
arxiv_to_prompt-0.5.1.dist-info/entry_points.txt
arxiv_to_prompt-0.5.1.dist-info/top_level.txt
arxiv_to_prompt-0.5.1.dist-info/RECORD
