Metadata-Version: 2.4
Name: arxiv-to-prompt
Version: 0.5.1
Summary: transform arXiv papers into a single latex prompt for LLMs
Author: Takashi Ishida
License: MIT
Project-URL: Homepage, https://github.com/takashiishida/arxiv-to-prompt
Project-URL: Changelog, https://github.com/takashiishida/arxiv-to-prompt/releases
Project-URL: Issues, https://github.com/takashiishida/arxiv-to-prompt/issues
Project-URL: CI, https://github.com/takashiishida/arxiv-to-prompt/actions
Requires-Python: >=3.8
License-File: LICENSE
Requires-Dist: requests>=2.25.0
Provides-Extra: test
Requires-Dist: pytest>=7.0.0; extra == "test"
Requires-Dist: pytest-cov>=4.0.0; extra == "test"
Dynamic: license-file
